f_program/__init__.py
f_program/__main__.py
f_program-0.7.dist-info/METADATA
f_program-0.7.dist-info/WHEEL
f_program-0.7.dist-info/entry_points.txt
f_program-0.7.dist-info/top_level.txt
f_program-0.7.dist-info/RECORD
